COPYING
MANIFEST.in
README.md
description.rst
setup.cfg
setup.py
waa2wls-protocol.txt
docs/.gitignore
docs/source/conf.py
docs/source/index.rst
docs/source/misc.rst
docs/source/modules.rst
docs/source/quickstart.rst
docs/source/security.rst
docs/source/ucam_webauth.rst
docs/source/ucam_webauth_raven.rst
python_ucam_webauth.egg-info/PKG-INFO
python_ucam_webauth.egg-info/SOURCES.txt
python_ucam_webauth.egg-info/dependency_links.txt
python_ucam_webauth.egg-info/requires.txt
python_ucam_webauth.egg-info/top_level.txt
ucam_webauth/__init__.py
ucam_webauth/flask_glue.py
ucam_webauth/rsa.c
ucam_webauth/raven/__init__.py
ucam_webauth/raven/demoserver.py
ucam_webauth/raven/flask_glue.py
ucam_webauth/raven/keys/pubkey2
ucam_webauth/raven/keys/pubkey901