Metadata-Version: 1.1
Name: python-ucam-webauth
Version: 0.9.2
Summary: Ucam-webauth and Raven application agent in Python
Home-page: http://github.com/danielrichman/python-ucam-webauth
Author: Daniel Richman
Author-email: main@danielrichman.co.uk
License: BSD-2-Clause
Keywords: Raven Cambridge ucam-webauth
Platform: UNKNOWN
Classifier: Development Status :: 4 - Beta
Classifier: Intended Audience :: Developers
Classifier: License :: OSI Approved :: BSD License
Classifier: Operating System :: OS Independent
Classifier: Framework :: Flask
Classifier: Topic :: Internet :: WWW/HTTP :: Dynamic Content :: CGI Tools/Libraries
Classifier: Programming Language :: Python :: 2
Classifier: Programming Language :: Python :: 3
